jigeum/__init__.py
jigeum/seoul.py
jigeum-1.0.2.dist-info/METADATA
jigeum-1.0.2.dist-info/WHEEL
jigeum-1.0.2.dist-info/top_level.txt
jigeum-1.0.2.dist-info/RECORD
