Metadata-Version: 2.1
Name: jigeum
Version: 1.0.2
Summary: jigeum seoul now
Author-email: dMario24 <data.mario24@gmail.com>
License: MIT
Project-URL: Homepage, https://github.com/dMario24/jigeum
Project-URL: Issues, https://github.com/dMario24/jigeum/issues
Requires-Python: >=3.9
Requires-Dist: pytz>=2024.2
